{
  "name": "@hebilicious/cssforge",
  "version": "0.1.0",
  "license": "MIT",
  "exports": {
    ".": "./src/mod.ts",
    "./cli": "./src/cli.ts"
  },
  "fmt": {
    "lineWidth": 90
  },
  "nodeModulesDir": "none",
  "imports": {
    "citty": "npm:citty@0.1.6",
    "chokidar": "npm:chokidar@4.0.3",
    "@std/collections": "jsr:@std/collections@^1.1.3",
    "colorjs.io": "npm:colorjs.io@0.5.2",
    "utopia-core": "npm:utopia-core@1.6.0"
  },
  "publish": {
    "include": [
      "src/**/*.ts",
      "README.md"
    ]
  },
  "tasks": {
    "cli": "deno run -A ./src/cli.ts",
    "example:cli": "deno run -A ./src/cli.ts --prefix ./example/basic --mode css",
    "test:cli": "deno run -A ./src/cli.ts"
  }
}
